eyes17/Peripherals.py
eyes17/__init__.py
eyes17/achan.py
eyes17/commands_proto.py
eyes17/eyemath17.py
eyes17/eyeplot17.py
eyes17/eyes.py
eyes17/packet_handler.py
eyes17/sensorlist.py
eyes17/SENSORS/AD7718_class.py
eyes17/SENSORS/AD9833.py
eyes17/SENSORS/ADS1115.py
eyes17/SENSORS/ADS1248.py
eyes17/SENSORS/BH1750.py
eyes17/SENSORS/BMP180.py
eyes17/SENSORS/ComplementaryFilter.py
eyes17/SENSORS/HMC5883L.py
eyes17/SENSORS/Kalman.py
eyes17/SENSORS/MF522.py
eyes17/SENSORS/MLX90614.py
eyes17/SENSORS/MPU6050.py
eyes17/SENSORS/MPU925x.py
eyes17/SENSORS/SHT21.py
eyes17/SENSORS/SSD1306.py
eyes17/SENSORS/TSL2561.py
eyes17/SENSORS/__init__.py
eyes17/SENSORS/supported.py
eyes17GUI/BHCurve.py
eyes17GUI/MPU6050.py
eyes17GUI/QtVersion.py
eyes17GUI/RCtransient.py
eyes17GUI/RLCsteadystate.py
eyes17GUI/RLCtransient.py
eyes17GUI/RLtransient.py
eyes17GUI/XYplot.py
eyes17GUI/XYplot2.py
eyes17GUI/__init__.py
eyes17GUI/advanced_logger.py
eyes17GUI/diodeIV.py
eyes17GUI/driven-pendulum.py
eyes17GUI/drivenRodPendulum.py
eyes17GUI/dust_sensor.py
eyes17GUI/editor.py
eyes17GUI/experiment-list.py
eyes17GUI/filterCircuit.py
eyes17GUI/i2cLogger.py
eyes17GUI/induction.py
eyes17GUI/language.py
eyes17GUI/lightsensorlogger.py
eyes17GUI/logger.py
eyes17GUI/main.py
eyes17GUI/newtons_laws.py
eyes17GUI/npnCEout.py
eyes17GUI/pendulumVelocity.py
eyes17GUI/plotIV.py
eyes17GUI/pnpCEout.py
eyes17GUI/pt100.py
eyes17GUI/pythonSyntax.py
eyes17GUI/renumberHelpFiles.py
eyes17GUI/renumberIndex.py
eyes17GUI/rodPendulum.py
eyes17GUI/scope.py
eyes17GUI/server.py
eyes17GUI/soundBeats.py
eyes17GUI/soundFreqResp.py
eyes17GUI/soundVelocity.py
eyes17GUI/sr04dist.py
eyes17GUI/sr04dist_fft.py
eyes17GUI/terminal.py
eyes17GUI/test.py
eyes17GUI/thermocouplelogger.py
eyes17GUI/tof.py
eyes17GUI/translate_svg.py
eyes17GUI/translate_thread.py
eyes17GUI/utils.py
eyes17GUI/code/FourierTransform.py
eyes17GUI/code/RCdifferentiation.py
eyes17GUI/code/RCintegration.py
eyes17GUI/code/RCsteadyState.py
eyes17GUI/code/RCtransient.py
eyes17win-1.0.0.dist-info/LICENSE
eyes17win-1.0.0.dist-info/METADATA
eyes17win-1.0.0.dist-info/WHEEL
eyes17win-1.0.0.dist-info/entry_points.txt
eyes17win-1.0.0.dist-info/top_level.txt
eyes17win-1.0.0.dist-info/RECORD
