Metadata-Version: 2.1
Name: eyes17win
Version: 1.0.0
Summary: Python package for ExpEYES17
Home-page: https://github.com/csparkresearch/expeyes17
Author: Jithin B.P
Author-email: jithinbp@gmail.com
Project-URL: Source, https://github.com/expeyes/expeyes-programs
Project-URL: Read The Docs, https://expeyes.in
Project-URL: Buy Hardware, https://csparkresearch.in/expeyes17
Keywords: expeyes17 data-acquisition lab-at-home oscilloscope waveform-generator sensors physics
Classifier: Development Status :: 5 - Production/Stable
Classifier: Intended Audience :: Education
Classifier: Programming Language :: Python :: 3
Classifier: License :: OSI Approved :: MIT License
Classifier: Operating System :: OS Independent
Requires-Python: >=3
License-File: LICENSE
Requires-Dist: pyserial
Requires-Dist: numpy
Requires-Dist: scipy
Requires-Dist: PyQt5
Requires-Dist: matplotlib
Requires-Dist: pyqtgraph
